sonarqube/__init__.py
sonarqube/audit.py
sonarqube/sonar.py
sonarqube_client-0.0.5.dist-info/LICENSE.txt
sonarqube_client-0.0.5.dist-info/METADATA
sonarqube_client-0.0.5.dist-info/WHEEL
sonarqube_client-0.0.5.dist-info/top_level.txt
sonarqube_client-0.0.5.dist-info/RECORD
