Metadata-Version: 2.1
Name: sonarqube-client
Version: 0.0.5
Summary: Package that creates simple APIs to interact with SonarQube
Home-page: https://github.com/peterdeames/sonarqube-api
Keywords: sonar sonarqube
Classifier: Development Status :: 1 - Planning
Classifier: Intended Audience :: Developers
Classifier: Intended Audience :: System Administrators
Classifier: Programming Language :: Python
Classifier: Topic :: Utilities
Classifier: Operating System :: OS Independent
License-File: LICENSE.txt
Requires-Dist: requests
Requires-Dist: tabulate
